LICENSE
README.md
setup.py
papid_01_weblogin.egg-info/PKG-INFO
papid_01_weblogin.egg-info/SOURCES.txt
papid_01_weblogin.egg-info/dependency_links.txt
papid_01_weblogin.egg-info/top_level.txt
user_lib/__init__.py
user_lib/password_pkg/__init__.py
user_lib/password_pkg/data.py
user_lib/password_pkg/password_check.py
user_lib/user_pkg/user_check.py